{
    "task_desc": "pick_heat_then_place_in_recep-Plate-None-Shelf-7/trial_T20190906_193957_675049",
    "scene": {
        "scene_type": [
            0
        ],
        "agent_init": [],
        "init_actions": [],
        "required_objects": [
            {
                "name": "Plate_1",
                "location": [
                    {
                        "CounterTop_1": "on"
                    }
                ]
            },
            {
                "name": "Microwave_1"
            },
            {
                "name": "Shelf_1"
            }
        ]
    },
    "script": [
        {
            "action": "GotoLocation",
            "name": "Plate_1"
        },
        {
            "action": "PickupObject",
            "name": "Plate_1"
        },
        {
            "action": "GotoLocation",
            "name": "Microwave_1"
        },
        {
            "action": "OpenObject",
            "name": "Microwave_1"
        },
        {
            "action": "PutObject",
            "name": "Microwave_1"
        },
        {
            "action": "CloseObject",
            "name": "Microwave_1"
        },
        {
            "action": "ToggleObjectOn",
            "name": "Microwave_1"
        },
        {
            "action": "ToggleObjectOff",
            "name": "Microwave_1"
        },
        {
            "action": "OpenObject",
            "name": "Microwave_1"
        },
        {
            "action": "PickupObject",
            "name": "Plate_1"
        },
        {
            "action": "GotoLocation",
            "name": "Shelf_1"
        },
        {
            "action": "PutObject",
            "name": "Shelf_1"
        }
    ],
    "task_goals": [
        {
            "goal_id": 0,
            "object_states": [
                {
                    "name": "Plate_1",
                    "receptacle_name": "Shelf_1"
                },
                {
                    "name": "Plate_1",
                    "ObjectTemperature": "Hot"
                }
            ],
            "object_states_relation": "and"
        }
    ],
    "attributes": {
        "floor_plan": "FloorPlan7"
    }
}